loamy/__init__.py
loamy/py.typed
loamy/session.py
loamy-0.0.10.dist-info/METADATA
loamy-0.0.10.dist-info/WHEEL
loamy-0.0.10.dist-info/licenses/LICENSE
loamy-0.0.10.dist-info/RECORD
