Metadata-Version: 2.3
Name: loamy
Version: 0.0.10
Summary: This project allows you to execute a list of http operations asynchronously from within a synchronous context.
License-Expression: MIT
License-File: LICENSE
Requires-Python: >=3.10
Requires-Dist: aiodns>=3.2.0
Requires-Dist: aiohttp>=3.10.10
Requires-Dist: loguru>=0.7.2
Requires-Dist: pydantic>=2.9.2
Provides-Extra: uvloop
Requires-Dist: uvloop>=0.21.0; extra == 'uvloop'
